{
  "configs": [
    "2may-scheduler.xml"
  ],
  "secureProperties": [],
  "redeploymentEnabled": true,
  "name": "com.mycompany:2may-scheduler:1.0.0-SNAPSHOT",
  "minMuleVersion": "4.4.0",
  "requiredProduct": "MULE",
  "classLoaderModelLoaderDescriptor": {
    "id": "mule",
    "attributes": {
      "exportedPackages": [],
      "exportedResources": [
        "2may-scheduler.xml",
        "log4j2.xml"
      ]
    }
  },
  "bundleDescriptorLoader": {
    "id": "mule",
    "attributes": {}
  }
}